<?xml version="1.0" encoding="UTF-8"?>
<cronentries>
    <cron>
        <url>/match</url>
        <description>find buddies to all users</description>
        <schedule>every 1 minutes</schedule>
    </cron>
    <cron>
        <url>/event_handler</url>
        <description>EventNotifierServlet</description>
        <schedule>every day 11:31</schedule>
    </cron>
    <cron>
        <url>/send_gift</url>
        <description>GiftSendingServlet</description>
        <schedule>every 2 minutes</schedule>
    </cron>

</cronentries>